Metadata-Version: 2.1
Name: FreeWorkUT
Version: 0.0.11
Summary: 这是个测试版，正式版请检索FreeWork！
Author: Jhonie King(王骏诚)
Author-email: queenelsaofarendelle2022@gmail.com
License: MIT License
Keywords: python,Office,Excle,Word,File's operation
Classifier: Intended Audience :: Developers
Classifier: Operating System :: OS Independent
Classifier: Natural Language :: Chinese (Simplified)
Classifier: Programming Language :: Python
Classifier: Programming Language :: Python :: 2
Classifier: Programming Language :: Python :: 2.7
Classifier: Programming Language :: Python :: 3
Classifier: Programming Language :: Python :: 3.5
Classifier: Programming Language :: Python :: 3.6
Classifier: Programming Language :: Python :: 3.7
Classifier: Programming Language :: Python :: 3.8
Classifier: Topic :: Software Development :: Libraries
License-File: LICENSE.txt
Requires-Dist: openpyxl
Requires-Dist: python-docx
Requires-Dist: pytest-shutil
